[
    {
        "id": 1,
        "name": "Cukur King",
        "rating": 5.0,
        "description": "Layanan potong rambut Premium",
        "image": "/barbershop1.jpeg"
    },

    {
        "id": 2,
        "name": "zigzag barber",
        "rating": 4.3,
        "description": "Bikin makin gaya",
        "image": "/barbershop2.jpeg"
    },

    {
        "id": 3,
        "name": "Five-O",
        "rating": 4.6,
        "description": "Kraton gaya, raja puas",
        "image": "/barbershop3.jpeg"
    },

    {
        "id": 4,
        "name": "Four-O",
        "rating": 5.0,
        "description": "Style gahar, harga bersahabat",
        "image": "/barbershop4.jpeg"
    },

    {
        "id": 5,
        "name": "Yepi Saloon",
        "rating": 4.5,
        "description": "Potong cepet, mantap, harga ramah",
        "image": "/barbershop5.jpeg"
    }
]